CHANGES.txt
MANIFEST.in
README.txt
setup.cfg
setup.py
tox.ini
src/baker2.py
src/tests.py
src/baker2.egg-info/PKG-INFO
src/baker2.egg-info/SOURCES.txt
src/baker2.egg-info/dependency_links.txt
src/baker2.egg-info/top_level.txt
src/baker2.egg-info/zip-safe